{"_default": {"1": {"uuid": 321039002268467200, "unseen_movies": ["I Want to Eat Your Pancreas", "Killers of the Flower Moon"], "seen_movies": []}, "2": {"uuid": 230052156365996044, "unseen_movies": ["The Grim Adventures of the Kids Next Door"], "seen_movies": []}, "3": {"uuid": 321056087199711252, "unseen_movies": ["The Grim Adventures of the Kids Next Door", "rampage"], "seen_movies": []}, "4": {"uuid": 359147154054447114, "unseen_movies": ["X-Men"], "seen_movies": []}, "5": {"uuid": 239423967713034260, "unseen_movies": ["Sadako vs Kayako", "Return of The Living Dead"], "seen_movies": []}}}